osfm/__init__.py
osfm/__main__.py
osfm/client.py
osfm/clientfunc.py
osfm/server.py
osfm/utils.py
osfm-1.0.2.data/scripts/__main__.py
osfm-1.0.2.dist-info/licenses/LICENSE
osfm-1.0.2.dist-info/METADATA
osfm-1.0.2.dist-info/WHEEL
osfm-1.0.2.dist-info/top_level.txt
osfm-1.0.2.dist-info/RECORD
