Metadata-Version: 2.4
Name: osfm
Version: 1.0.2
Summary: OSFM - Network System Management Made Simple
Author-email: Rishikesh Giridhar <rishikesh.giridhar@outlook.com>
License:                     GNU GENERAL PUBLIC LICENSE
Project-URL: Homepage, https://osfm-site.vercel.app/
Project-URL: Repository, https://github.com/RishiSpace/osfm/tree/osfm-py
Requires-Python: >=3.11
License-File: LICENSE
Requires-Dist: PyQt5
Requires-Dist: win10toast
Requires-Dist: plyer
Dynamic: license-file
